README.md
setup.cfg
setup.py
nwmodule/__init__.py
nwmodule/logger.py
nwmodule/nwmodule.py
nwmodule/serializer.py
nwmodule/types.py
nwmodule.egg-info/PKG-INFO
nwmodule.egg-info/SOURCES.txt
nwmodule.egg-info/dependency_links.txt
nwmodule.egg-info/requires.txt
nwmodule.egg-info/top_level.txt
nwmodule/callbacks/__init__.py
nwmodule/callbacks/callback.py
nwmodule/callbacks/early_stopping.py
nwmodule/callbacks/plot_metrics.py
nwmodule/callbacks/random_plot_each_epoch.py
nwmodule/callbacks/save_history.py
nwmodule/callbacks/save_models.py
nwmodule/loss/__init__.py
nwmodule/loss/bce.py
nwmodule/loss/l1.py
nwmodule/loss/l2.py
nwmodule/loss/nll.py
nwmodule/metrics/__init__.py
nwmodule/metrics/loss.py
nwmodule/metrics/metric.py
nwmodule/metrics/metric_wrapper.py
nwmodule/models/__init__.py
nwmodule/models/generator_network.py
nwmodule/models/variational_autoencoder_network.py
nwmodule/models/feed_forward/__init__.py
nwmodule/models/feed_forward/feed_forward_network.py
nwmodule/models/feed_forward/feed_forward_trainer.py
nwmodule/models/generative_adversarial_network/__init__.py
nwmodule/models/generative_adversarial_network/gan_trainer.py
nwmodule/models/generative_adversarial_network/generative_adversarial_network.py
nwmodule/schedulers/__init__.py
nwmodule/schedulers/reduce_lr_and_backtrace_on_plateau.py
nwmodule/schedulers/reduce_lr_on_plateau.py
nwmodule/trainer/__init__.py
nwmodule/trainer/nwtrainer.py
nwmodule/trainer/setup_module_for_train.py
test/__init__.py