Metadata-Version: 2.1
Name: nwmodule
Version: 0.6
Summary: Generic PyTorch high level neural API
Home-page: https://gitlab.com/neuralwrappers/nwmodule
Author: Mihai Cristian Pîrvu
Author-email: mihaicristianpirvu@gmail.com
License: WTFPL
Keywords: PyTorch,neural network,high level api
Platform: UNKNOWN
Classifier: Programming Language :: Python :: 3
Classifier: Operating System :: OS Independent
Requires-Python: >=3.8
